charon/__init__.py
charon/__main__.py
charon/requirements.txt
charon/restic.py
charon/scheduling.py
charon/shared.py
charon/styx.py
charon/sources/__init__.py
charon/sources/http.py
charon/sources/local.py
charon/sources/sqlite.py
haondt_charon-2.2.1.dist-info/entry_points.txt
haondt_charon-2.2.1.dist-info/LICENSE
haondt_charon-2.2.1.dist-info/WHEEL
haondt_charon-2.2.1.dist-info/METADATA
haondt_charon-2.2.1.dist-info/RECORD
