Metadata-Version: 2.3
Name: haondt_charon
Version: 2.2.1
Summary: charon is a utility for backing up data from one location to another at regular intervals.
Keywords: backup,recovery
Author: haondt
Classifier: License :: OSI Approved :: MIT License
Requires-Dist: croniter>=2.0.5
Requires-Dist: PyYAML>=6.0.1
Requires-Dist: jq>=1.8.0
Requires-Dist: requests==2.32.5
Project-URL: Homepage, https://gitlab.com/haondt/charon
Project-URL: Repository, https://gitlab.com/haondt/charon
